enpy/__init__.py
enpy-1.0.0.dist-info/METADATA
enpy-1.0.0.dist-info/WHEEL
enpy-1.0.0.dist-info/top_level.txt
enpy-1.0.0.dist-info/RECORD
