Metadata-Version: 2.1
Name: enpy
Version: 1.0.0
Summary: An encryption/decryption program that incorporates OTP
Home-page: UNKNOWN
Author: Divit Kanath
Author-email: divitkanath@gmail.com
License: MIT
Keywords: encryption,decryption
Platform: UNKNOWN
Classifier: Development Status :: 5 - Production/Stable
Classifier: Intended Audience :: Developers
Classifier: Operating System :: Unix
Classifier: License :: OSI Approved :: MIT License
Classifier: Programming Language :: Python :: 3
Classifier: Programming Language :: Python :: 3.7
Classifier: Programming Language :: Python :: 3.8
Classifier: Programming Language :: Python :: 3.9
